LICENSE.rst
MANIFEST.in
README.rst
setup.py
django_shop_simplevariations.egg-info/PKG-INFO
django_shop_simplevariations.egg-info/SOURCES.txt
django_shop_simplevariations.egg-info/dependency_links.txt
django_shop_simplevariations.egg-info/not-zip-safe
django_shop_simplevariations.egg-info/requires.txt
django_shop_simplevariations.egg-info/top_level.txt
docs/product-variations.rst
shop_simplevariations/__init__.py
shop_simplevariations/admin.py
shop_simplevariations/cart_modifier.py
shop_simplevariations/models.py
shop_simplevariations/urls.py
shop_simplevariations/views.py
shop_simplevariations/migrations/0001_initial.py
shop_simplevariations/migrations/0002_auto__add_cartitemtextoption.py
shop_simplevariations/migrations/0003_auto__add_textoption__del_field_cartitemtextoption_price__add_field_ca.py
shop_simplevariations/migrations/0004_auto__del_field_textoption_description__add_field_textoption_name.py
shop_simplevariations/migrations/0005_auto__add_field_textoption_description.py
shop_simplevariations/migrations/__init__.py
shop_simplevariations/templatetags/__init__.py
shop_simplevariations/templatetags/simplevariation_tags.py
shop_simplevariations/tests/__init__.py
shop_simplevariations/tests/cart_modifier.py
shop_simplevariations/tests/simplevariation_tags.py
shop_simplevariations/tests/test_utils.py
shop_simplevariations/tests/views.py